[
  {
    "date": "2024-04-12",
    "rain": 98.5,
    "min_temp": null,
    "max_temp": null
  },
  {
    "date": "2024-04-14",
    "rain": 14.5,
    "min_temp": null,
    "max_temp": null
  },
  {
    "date": "2024-04-16",
    "rain": 23.5,
    "min_temp": null,
    "max_temp": null
  },
  {
    "date": "2024-04-22",
    "rain": 44.5,
    "min_temp": null,
    "max_temp": null
  },
  {
    "date": "2024-04-27",
    "rain": 2.0,
    "min_temp": null,
    "max_temp": null
  },
  {
    "date": "2024-05-02",
    "rain": 18.5,
    "min_temp": null,
    "max_temp": null
  },
  {
    "date": "2024-05-18",
    "rain": 40.5,
    "min_temp": null,
    "max_temp": null
  },
  {
    "date": "2024-05-20",
    "rain": 98.5,
    "min_temp": null,
    "max_temp": null
  },
  {
    "date": "2024-05-21",
    "rain": 79.5,
    "min_temp": null,
    "max_temp": null
  },
  {
    "date": "2024-05-24",
    "rain": 34.5,
    "min_temp": null,
    "max_temp": null
  },
  {
    "date": "2024-06-01",
    "rain": 97.0,
    "min_temp": null,
    "max_temp": null
  },
  {
    "date": "2024-06-02",
    "rain": 349.0,
    "min_temp": null,
    "max_temp": null
  },
  {
    "date": "2024-06-08",
    "rain": 45.0,
    "min_temp": null,
    "max_temp": null
  },
  {
    "date": "2024-06-13",
    "rain": 13.0,
    "min_temp": null,
    "max_temp": null
  },
  {
    "date": "2024-06-26",
    "rain": 30.0,
    "min_temp": null,
    "max_temp": null
  },
  {
    "date": "2024-07-06",
    "rain": 105.0,
    "min_temp": null,
    "max_temp": null
  },
  {
    "date": "2024-07-13",
    "rain": 11.5,
    "min_temp": null,
    "max_temp": null
  },
  {
    "date": "2024-07-14",
    "rain": 69.0,
    "min_temp": null,
    "max_temp": null
  },
  {
    "date": "2024-07-17",
    "rain": 10.5,
    "min_temp": null,
    "max_temp": null
  },
  {
    "date": "2024-07-18",
    "rain": 15.0,
    "min_temp": null,
    "max_temp": null
  },
  {
    "date": "2024-08-01",
    "rain": 53.0,
    "min_temp": null,
    "max_temp": null
  },
  {
    "date": "2024-08-18",
    "rain": 76.0,
    "min_temp": null,
    "max_temp": null
  },
  {
    "date": "2024-08-30",
    "rain": 19.0,
    "min_temp": null,
    "max_temp": null
  },
  {
    "date": "2024-09-04",
    "rain": 24.5,
    "min_temp": null,
    "max_temp": null
  },
  {
    "date": "2024-09-05",
    "rain": 23.0,
    "min_temp": null,
    "max_temp": null
  },
  {
    "date": "2024-09-06",
    "rain": 7.5,
    "min_temp": null,
    "max_temp": null
  },
  {
    "date": "2024-09-09",
    "rain": 22.5,
    "min_temp": null,
    "max_temp": null
  },
  {
    "date": "2024-09-15",
    "rain": 9.0,
    "min_temp": null,
    "max_temp": null
  },
  {
    "date": "2024-09-16",
    "rain": 7.0,
    "min_temp": null,
    "max_temp": null
  },
  {
    "date": "2024-09-17",
    "rain": 5.0,
    "min_temp": null,
    "max_temp": null
  },
  {
    "date": "2024-10-06",
    "rain": 1.5,
    "min_temp": null,
    "max_temp": null
  },
  {
    "date": "2024-10-08",
    "rain": 104.5,
    "min_temp": null,
    "max_temp": null
  },
  {
    "date": "2024-10-14",
    "rain": 72.0,
    "min_temp": null,
    "max_temp": null
  },
  {
    "date": "2024-10-30",
    "rain": 10.0,
    "min_temp": null,
    "max_temp": null
  },
  {
    "date": "2024-11-03",
    "rain": 65.5,
    "min_temp": null,
    "max_temp": null
  },
  {
    "date": "2024-11-06",
    "rain": 44.0,
    "min_temp": null,
    "max_temp": null
  },
  {
    "date": "2024-11-21",
    "rain": 64.0,
    "min_temp": null,
    "max_temp": null
  },
  {
    "date": "2025-01-24",
    "rain": 9.0,
    "min_temp": null,
    "max_temp": null
  },
  {
    "date": "2025-03-02",
    "rain": 50.0,
    "min_temp": null,
    "max_temp": null
  },
  {
    "date": "2025-03-15",
    "rain": 18.5,
    "min_temp": null,
    "max_temp": null
  },
  {
    "date": "2025-03-18",
    "rain": 40.0,
    "min_temp": null,
    "max_temp": null
  },
  {
    "date": "2025-03-23",
    "rain": 73.5,
    "min_temp": null,
    "max_temp": null
  },
  {
    "date": "2025-03-25",
    "rain": 13.0,
    "min_temp": null,
    "max_temp": null
  },
  {
    "date": "2025-04-09",
    "rain": 32.0,
    "min_temp": null,
    "max_temp": null
  },
  {
    "date": "2025-04-11",
    "rain": 32.5,
    "min_temp": null,
    "max_temp": null
  },
  {
    "date": "2025-04-14",
    "rain": 8.0,
    "min_temp": null,
    "max_temp": null
  },
  {
    "date": "2025-04-22",
    "rain": 36.5,
    "min_temp": null,
    "max_temp": null
  },
  {
    "date": "2025-04-25",
    "rain": 38.5,
    "min_temp": null,
    "max_temp": null
  },
  {
    "date": "2025-04-27",
    "rain": 22.0,
    "min_temp": null,
    "max_temp": null
  },
  {
    "date": "2025-06-29",
    "rain": 8.0,
    "min_temp": null,
    "max_temp": null
  },
  {
    "date": "2025-07-03",
    "rain": 0.5,
    "min_temp": null,
    "max_temp": null
  },
  {
    "date": "2025-07-05",
    "rain": 1.5,
    "min_temp": null,
    "max_temp": null
  },
  {
    "date": "2025-07-08",
    "rain": 4.0,
    "min_temp": null,
    "max_temp": null
  },
  {
    "date": "2025-07-11",
    "rain": 5.5,
    "min_temp": null,
    "max_temp": null
  },
  {
    "date": "2025-07-12",
    "rain": 5.0,
    "min_temp": null,
    "max_temp": null
  },
  {
    "date": "2025-07-14",
    "rain": 11.0,
    "min_temp": null,
    "max_temp": null
  },
  {
    "date": "2025-07-20",
    "rain": 14.0,
    "min_temp": null,
    "max_temp": null
  },
  {
    "date": "2025-07-26",
    "rain": 31.0,
    "min_temp": null,
    "max_temp": null
  },
  {
    "date": "2025-08-05",
    "rain": 9.0,
    "min_temp": null,
    "max_temp": null
  },
  {
    "date": "2025-08-11",
    "rain": 24.0,
    "min_temp": null,
    "max_temp": null
  },
  {
    "date": "2025-08-12",
    "rain": 19.5,
    "min_temp": null,
    "max_temp": null
  },
  {
    "date": "2025-08-13",
    "rain": 18.5,
    "min_temp": null,
    "max_temp": null
  },
  {
    "date": "2025-08-14",
    "rain": 28.0,
    "min_temp": null,
    "max_temp": null
  },
  {
    "date": "2025-08-19",
    "rain": 0.5,
    "min_temp": null,
    "max_temp": null
  },
  {
    "date": "2025-09-17",
    "rain": 38.5,
    "min_temp": null,
    "max_temp": null
  },
  {
    "date": "2025-09-19",
    "rain": 62.5,
    "min_temp": null,
    "max_temp": null
  },
  {
    "date": "2025-09-28",
    "rain": 11.5,
    "min_temp": null,
    "max_temp": null
  }
]