[
  {
    "date": "2024-04-06",
    "rain": 14.0,
    "min_temp": null,
    "max_temp": null
  },
  {
    "date": "2024-10-12",
    "rain": 121.5,
    "min_temp": null,
    "max_temp": null
  },
  {
    "date": "2024-10-14",
    "rain": 72.0,
    "min_temp": null,
    "max_temp": null
  },
  {
    "date": "2024-10-30",
    "rain": 10.0,
    "min_temp": null,
    "max_temp": null
  },
  {
    "date": "2024-11-03",
    "rain": 65.5,
    "min_temp": null,
    "max_temp": null
  },
  {
    "date": "2024-11-06",
    "rain": 44.0,
    "min_temp": null,
    "max_temp": null
  },
  {
    "date": "2024-11-21",
    "rain": 64.0,
    "min_temp": null,
    "max_temp": null
  },
  {
    "date": "2025-04-27",
    "rain": 22.0,
    "min_temp": null,
    "max_temp": null
  },
  {
    "date": "2025-07-03",
    "rain": 1.0,
    "min_temp": null,
    "max_temp": null
  },
  {
    "date": "2025-07-07",
    "rain": 14.0,
    "min_temp": null,
    "max_temp": null
  },
  {
    "date": "2025-07-11",
    "rain": 3.0,
    "min_temp": null,
    "max_temp": null
  },
  {
    "date": "2025-07-26",
    "rain": 25.5,
    "min_temp": null,
    "max_temp": null
  }
]