[
  {
    "date": "2024-04-12",
    "rain": 65.5,
    "min_temp": null,
    "max_temp": null
  },
  {
    "date": "2024-04-14",
    "rain": 11.0,
    "min_temp": null,
    "max_temp": null
  },
  {
    "date": "2024-04-15",
    "rain": 71.0,
    "min_temp": null,
    "max_temp": null
  },
  {
    "date": "2024-04-23",
    "rain": 21.5,
    "min_temp": null,
    "max_temp": null
  },
  {
    "date": "2024-04-27",
    "rain": 1.5,
    "min_temp": null,
    "max_temp": null
  },
  {
    "date": "2024-08-21",
    "rain": 105.5,
    "min_temp": null,
    "max_temp": null
  },
  {
    "date": "2024-12-30",
    "rain": 13.5,
    "min_temp": null,
    "max_temp": null
  },
  {
    "date": "2025-01-01",
    "rain": 36.5,
    "min_temp": null,
    "max_temp": null
  },
  {
    "date": "2025-02-06",
    "rain": 0.5,
    "min_temp": null,
    "max_temp": null
  },
  {
    "date": "2025-02-16",
    "rain": 3.5,
    "min_temp": null,
    "max_temp": null
  },
  {
    "date": "2025-03-30",
    "rain": 8.0,
    "min_temp": null,
    "max_temp": null
  },
  {
    "date": "2025-04-09",
    "rain": 27.5,
    "min_temp": null,
    "max_temp": null
  },
  {
    "date": "2025-04-12",
    "rain": 49.5,
    "min_temp": null,
    "max_temp": null
  },
  {
    "date": "2025-04-15",
    "rain": 18.0,
    "min_temp": null,
    "max_temp": null
  },
  {
    "date": "2025-07-06",
    "rain": 10.0,
    "min_temp": null,
    "max_temp": null
  },
  {
    "date": "2025-08-08",
    "rain": 0.5,
    "min_temp": null,
    "max_temp": null
  },
  {
    "date": "2025-08-15",
    "rain": 11.5,
    "min_temp": null,
    "max_temp": null
  },
  {
    "date": "2025-08-25",
    "rain": 0.5,
    "min_temp": null,
    "max_temp": null
  },
  {
    "date": "2025-09-14",
    "rain": 3.0,
    "min_temp": null,
    "max_temp": null
  },
  {
    "date": "2025-09-29",
    "rain": 2.5,
    "min_temp": null,
    "max_temp": null
  }
]