[
  {
    "date": "2021-07-12",
    "rain": 3.6,
    "min_temp": null,
    "max_temp": null
  },
  {
    "date": "2021-12-02",
    "rain": 24.2,
    "min_temp": null,
    "max_temp": null
  },
  {
    "date": "2021-12-06",
    "rain": 56.0,
    "min_temp": null,
    "max_temp": null
  },
  {
    "date": "2021-12-22",
    "rain": 7.0,
    "min_temp": null,
    "max_temp": null
  },
  {
    "date": "2021-12-23",
    "rain": 37.5,
    "min_temp": null,
    "max_temp": null
  },
  {
    "date": "2022-01-06",
    "rain": 24.5,
    "min_temp": null,
    "max_temp": null
  },
  {
    "date": "2022-01-18",
    "rain": 8.7,
    "min_temp": null,
    "max_temp": null
  },
  {
    "date": "2022-02-23",
    "rain": 10.3,
    "min_temp": null,
    "max_temp": null
  },
  {
    "date": "2022-03-16",
    "rain": 4.5,
    "min_temp": null,
    "max_temp": null
  },
  {
    "date": "2022-08-08",
    "rain": 2.1,
    "min_temp": null,
    "max_temp": null
  },
  {
    "date": "2022-11-10",
    "rain": 52.1,
    "min_temp": null,
    "max_temp": null
  },
  {
    "date": "2022-11-28",
    "rain": 99.6,
    "min_temp": null,
    "max_temp": null
  },
  {
    "date": "2022-12-15",
    "rain": 30.2,
    "min_temp": null,
    "max_temp": null
  },
  {
    "date": "2023-01-25",
    "rain": 12.5,
    "min_temp": null,
    "max_temp": null
  },
  {
    "date": "2023-02-07",
    "rain": 38.5,
    "min_temp": null,
    "max_temp": null
  },
  {
    "date": "2023-04-11",
    "rain": 5.2,
    "min_temp": null,
    "max_temp": null
  },
  {
    "date": "2023-04-24",
    "rain": 45.5,
    "min_temp": null,
    "max_temp": null
  },
  {
    "date": "2023-05-15",
    "rain": 73.2,
    "min_temp": null,
    "max_temp": null
  },
  {
    "date": "2023-08-18",
    "rain": 3.5,
    "min_temp": null,
    "max_temp": null
  },
  {
    "date": "2023-09-11",
    "rain": 31.0,
    "min_temp": null,
    "max_temp": null
  },
  {
    "date": "2023-09-19",
    "rain": 17.0,
    "min_temp": null,
    "max_temp": null
  },
  {
    "date": "2023-11-01",
    "rain": 32.0,
    "min_temp": null,
    "max_temp": null
  },
  {
    "date": "2023-11-10",
    "rain": 81.5,
    "min_temp": null,
    "max_temp": null
  },
  {
    "date": "2023-11-17",
    "rain": 86.1,
    "min_temp": null,
    "max_temp": null
  },
  {
    "date": "2024-01-04",
    "rain": 12.0,
    "min_temp": null,
    "max_temp": null
  },
  {
    "date": "2024-02-02",
    "rain": 62.0,
    "min_temp": null,
    "max_temp": null
  }
]