[
  {
    "date": "2021-07-10",
    "rain": 96.0,
    "min_temp": null,
    "max_temp": null
  },
  {
    "date": "2021-09-25",
    "rain": 64.0,
    "min_temp": null,
    "max_temp": null
  },
  {
    "date": "2021-10-03",
    "rain": 10.0,
    "min_temp": null,
    "max_temp": null
  },
  {
    "date": "2021-12-02",
    "rain": 13.7,
    "min_temp": null,
    "max_temp": null
  },
  {
    "date": "2022-01-09",
    "rain": 53.2,
    "min_temp": null,
    "max_temp": null
  },
  {
    "date": "2022-02-28",
    "rain": 26.5,
    "min_temp": null,
    "max_temp": null
  },
  {
    "date": "2022-04-10",
    "rain": 60.0,
    "min_temp": null,
    "max_temp": null
  },
  {
    "date": "2022-05-12",
    "rain": 10.0,
    "min_temp": null,
    "max_temp": null
  },
  {
    "date": "2022-06-01",
    "rain": 50.4,
    "min_temp": null,
    "max_temp": null
  },
  {
    "date": "2022-10-01",
    "rain": 22.1,
    "min_temp": null,
    "max_temp": null
  },
  {
    "date": "2022-11-08",
    "rain": 47.4,
    "min_temp": null,
    "max_temp": null
  },
  {
    "date": "2023-01-26",
    "rain": 21.7,
    "min_temp": null,
    "max_temp": null
  }
]