[
  {
    "date": "2021-10-09",
    "rain": 9.9,
    "min_temp": null,
    "max_temp": null
  },
  {
    "date": "2021-10-23",
    "rain": 46.0,
    "min_temp": null,
    "max_temp": null
  },
  {
    "date": "2021-11-09",
    "rain": 260.0,
    "min_temp": null,
    "max_temp": null
  },
  {
    "date": "2021-11-14",
    "rain": 31.0,
    "min_temp": null,
    "max_temp": null
  },
  {
    "date": "2021-11-23",
    "rain": 17.3,
    "min_temp": null,
    "max_temp": null
  },
  {
    "date": "2022-04-22",
    "rain": 79.1,
    "min_temp": null,
    "max_temp": null
  },
  {
    "date": "2022-08-31",
    "rain": 67.0,
    "min_temp": null,
    "max_temp": null
  },
  {
    "date": "2022-11-06",
    "rain": 33.2,
    "min_temp": null,
    "max_temp": null
  },
  {
    "date": "2022-12-20",
    "rain": 79.0,
    "min_temp": null,
    "max_temp": null
  },
  {
    "date": "2023-02-05",
    "rain": 14.6,
    "min_temp": null,
    "max_temp": null
  },
  {
    "date": "2023-08-16",
    "rain": 0.0,
    "min_temp": null,
    "max_temp": null
  },
  {
    "date": "2023-08-21",
    "rain": 0.0,
    "min_temp": null,
    "max_temp": null
  },
  {
    "date": "2023-08-25",
    "rain": 0.0,
    "min_temp": null,
    "max_temp": null
  },
  {
    "date": "2023-11-04",
    "rain": 53.1,
    "min_temp": null,
    "max_temp": null
  },
  {
    "date": "2023-11-25",
    "rain": 19.2,
    "min_temp": null,
    "max_temp": null
  },
  {
    "date": "2023-12-26",
    "rain": 0.0,
    "min_temp": null,
    "max_temp": null
  },
  {
    "date": "2024-01-25",
    "rain": 0.0,
    "min_temp": null,
    "max_temp": null
  },
  {
    "date": "2024-02-12",
    "rain": 0.0,
    "min_temp": null,
    "max_temp": null
  }
]