[
  {
    "date": "2018-11-07",
    "rain": 187.0,
    "min_temp": null,
    "max_temp": null
  },
  {
    "date": "2018-11-12",
    "rain": 0.0,
    "min_temp": null,
    "max_temp": null
  },
  {
    "date": "2019-02-04",
    "rain": 21.0,
    "min_temp": null,
    "max_temp": null
  },
  {
    "date": "2019-02-21",
    "rain": 0.0,
    "min_temp": null,
    "max_temp": null
  },
  {
    "date": "2019-06-29",
    "rain": 0.0,
    "min_temp": null,
    "max_temp": null
  },
  {
    "date": "2019-07-07",
    "rain": 0.0,
    "min_temp": null,
    "max_temp": null
  },
  {
    "date": "2019-11-29",
    "rain": 65.3,
    "min_temp": null,
    "max_temp": null
  },
  {
    "date": "2019-12-03",
    "rain": 104.3,
    "min_temp": null,
    "max_temp": null
  },
  {
    "date": "2020-01-22",
    "rain": 15.5,
    "min_temp": null,
    "max_temp": null
  },
  {
    "date": "2021-02-02",
    "rain": 0.0,
    "min_temp": null,
    "max_temp": null
  },
  {
    "date": "2021-07-21",
    "rain": 0.0,
    "min_temp": null,
    "max_temp": null
  },
  {
    "date": "2021-07-30",
    "rain": 0.0,
    "min_temp": null,
    "max_temp": null
  },
  {
    "date": "2021-07-31",
    "rain": 0.0,
    "min_temp": null,
    "max_temp": null
  },
  {
    "date": "2021-08-09",
    "rain": 55.0,
    "min_temp": null,
    "max_temp": null
  },
  {
    "date": "2021-08-10",
    "rain": 22.9,
    "min_temp": null,
    "max_temp": null
  },
  {
    "date": "2021-08-18",
    "rain": 5.5,
    "min_temp": null,
    "max_temp": null
  },
  {
    "date": "2021-08-25",
    "rain": 6.0,
    "min_temp": null,
    "max_temp": null
  },
  {
    "date": "2021-09-26",
    "rain": 7.6,
    "min_temp": null,
    "max_temp": null
  },
  {
    "date": "2021-10-01",
    "rain": 26.0,
    "min_temp": null,
    "max_temp": null
  },
  {
    "date": "2021-12-26",
    "rain": 0.0,
    "min_temp": null,
    "max_temp": null
  },
  {
    "date": "2021-12-28",
    "rain": 0.0,
    "min_temp": null,
    "max_temp": null
  },
  {
    "date": "2021-12-30",
    "rain": 9.5,
    "min_temp": null,
    "max_temp": null
  },
  {
    "date": "2022-01-03",
    "rain": 70.0,
    "min_temp": null,
    "max_temp": null
  },
  {
    "date": "2022-01-04",
    "rain": 103.4,
    "min_temp": null,
    "max_temp": null
  },
  {
    "date": "2022-01-05",
    "rain": 31.4,
    "min_temp": null,
    "max_temp": null
  },
  {
    "date": "2022-01-10",
    "rain": 40.0,
    "min_temp": null,
    "max_temp": null
  },
  {
    "date": "2022-01-26",
    "rain": 0.0,
    "min_temp": null,
    "max_temp": null
  },
  {
    "date": "2022-02-10",
    "rain": 36.0,
    "min_temp": null,
    "max_temp": null
  },
  {
    "date": "2022-02-16",
    "rain": 0.0,
    "min_temp": null,
    "max_temp": null
  },
  {
    "date": "2022-02-17",
    "rain": 0.0,
    "min_temp": null,
    "max_temp": null
  },
  {
    "date": "2022-02-18",
    "rain": 0.0,
    "min_temp": null,
    "max_temp": null
  },
  {
    "date": "2022-02-22",
    "rain": 0.0,
    "min_temp": null,
    "max_temp": null
  },
  {
    "date": "2022-03-02",
    "rain": 2.0,
    "min_temp": null,
    "max_temp": null
  },
  {
    "date": "2022-03-07",
    "rain": 13.7,
    "min_temp": null,
    "max_temp": null
  },
  {
    "date": "2022-03-17",
    "rain": 0.0,
    "min_temp": null,
    "max_temp": null
  },
  {
    "date": "2022-03-18",
    "rain": 29.0,
    "min_temp": null,
    "max_temp": null
  },
  {
    "date": "2022-06-14",
    "rain": 0.0,
    "min_temp": null,
    "max_temp": null
  },
  {
    "date": "2022-06-22",
    "rain": 11.0,
    "min_temp": null,
    "max_temp": null
  },
  {
    "date": "2022-07-09",
    "rain": 0.0,
    "min_temp": null,
    "max_temp": null
  },
  {
    "date": "2022-07-10",
    "rain": 0.0,
    "min_temp": null,
    "max_temp": null
  },
  {
    "date": "2022-07-13",
    "rain": 0.0,
    "min_temp": null,
    "max_temp": null
  },
  {
    "date": "2022-08-11",
    "rain": 0.0,
    "min_temp": null,
    "max_temp": null
  },
  {
    "date": "2022-08-12",
    "rain": 0.0,
    "min_temp": null,
    "max_temp": null
  },
  {
    "date": "2022-08-13",
    "rain": 0.0,
    "min_temp": null,
    "max_temp": null
  },
  {
    "date": "2022-08-14",
    "rain": 0.0,
    "min_temp": null,
    "max_temp": null
  },
  {
    "date": "2022-08-31",
    "rain": 57.7,
    "min_temp": null,
    "max_temp": null
  },
  {
    "date": "2022-09-17",
    "rain": 0.0,
    "min_temp": null,
    "max_temp": null
  },
  {
    "date": "2022-09-18",
    "rain": 0.0,
    "min_temp": null,
    "max_temp": null
  },
  {
    "date": "2022-09-24",
    "rain": 0.0,
    "min_temp": null,
    "max_temp": null
  },
  {
    "date": "2022-09-25",
    "rain": 0.0,
    "min_temp": null,
    "max_temp": null
  },
  {
    "date": "2022-10-26",
    "rain": 32.0,
    "min_temp": null,
    "max_temp": null
  },
  {
    "date": "2022-10-29",
    "rain": 0.0,
    "min_temp": null,
    "max_temp": null
  },
  {
    "date": "2022-11-03",
    "rain": 31.0,
    "min_temp": null,
    "max_temp": null
  },
  {
    "date": "2022-11-10",
    "rain": 43.4,
    "min_temp": null,
    "max_temp": null
  },
  {
    "date": "2022-11-18",
    "rain": 0.0,
    "min_temp": null,
    "max_temp": null
  },
  {
    "date": "2022-11-21",
    "rain": 0.0,
    "min_temp": null,
    "max_temp": null
  },
  {
    "date": "2022-11-22",
    "rain": 0.0,
    "min_temp": null,
    "max_temp": null
  },
  {
    "date": "2022-11-23",
    "rain": 0.0,
    "min_temp": null,
    "max_temp": null
  },
  {
    "date": "2022-11-24",
    "rain": 0.0,
    "min_temp": null,
    "max_temp": null
  },
  {
    "date": "2022-12-07",
    "rain": 0.0,
    "min_temp": null,
    "max_temp": null
  },
  {
    "date": "2022-12-08",
    "rain": 9.5,
    "min_temp": null,
    "max_temp": null
  },
  {
    "date": "2022-12-21",
    "rain": 35.3,
    "min_temp": null,
    "max_temp": null
  },
  {
    "date": "2023-01-01",
    "rain": 0.0,
    "min_temp": null,
    "max_temp": null
  },
  {
    "date": "2023-01-03",
    "rain": 0.0,
    "min_temp": null,
    "max_temp": null
  },
  {
    "date": "2023-01-12",
    "rain": 0.0,
    "min_temp": null,
    "max_temp": null
  },
  {
    "date": "2023-01-19",
    "rain": 0.0,
    "min_temp": null,
    "max_temp": null
  },
  {
    "date": "2023-01-20",
    "rain": 0.0,
    "min_temp": null,
    "max_temp": null
  },
  {
    "date": "2023-01-23",
    "rain": 27.5,
    "min_temp": null,
    "max_temp": null
  },
  {
    "date": "2023-02-12",
    "rain": 0.0,
    "min_temp": null,
    "max_temp": null
  },
  {
    "date": "2023-02-13",
    "rain": 0.0,
    "min_temp": null,
    "max_temp": null
  },
  {
    "date": "2023-02-16",
    "rain": 0.0,
    "min_temp": null,
    "max_temp": null
  },
  {
    "date": "2023-02-23",
    "rain": 0.0,
    "min_temp": null,
    "max_temp": null
  },
  {
    "date": "2023-02-24",
    "rain": 0.0,
    "min_temp": null,
    "max_temp": null
  },
  {
    "date": "2023-03-03",
    "rain": 0.0,
    "min_temp": null,
    "max_temp": null
  },
  {
    "date": "2023-04-11",
    "rain": 0.0,
    "min_temp": null,
    "max_temp": null
  },
  {
    "date": "2023-04-12",
    "rain": 0.0,
    "min_temp": null,
    "max_temp": null
  },
  {
    "date": "2023-05-25",
    "rain": 0.0,
    "min_temp": null,
    "max_temp": null
  },
  {
    "date": "2023-06-15",
    "rain": 0.0,
    "min_temp": null,
    "max_temp": null
  },
  {
    "date": "2023-06-18",
    "rain": 0.0,
    "min_temp": null,
    "max_temp": null
  },
  {
    "date": "2023-06-23",
    "rain": 29.0,
    "min_temp": null,
    "max_temp": null
  },
  {
    "date": "2023-07-12",
    "rain": 5.7,
    "min_temp": null,
    "max_temp": null
  },
  {
    "date": "2023-07-30",
    "rain": 0.0,
    "min_temp": null,
    "max_temp": null
  },
  {
    "date": "2023-07-31",
    "rain": 0.0,
    "min_temp": null,
    "max_temp": null
  },
  {
    "date": "2023-08-03",
    "rain": 0.0,
    "min_temp": null,
    "max_temp": null
  },
  {
    "date": "2023-08-06",
    "rain": 0.0,
    "min_temp": null,
    "max_temp": null
  },
  {
    "date": "2023-08-15",
    "rain": 0.0,
    "min_temp": null,
    "max_temp": null
  },
  {
    "date": "2023-08-17",
    "rain": 0.0,
    "min_temp": null,
    "max_temp": null
  },
  {
    "date": "2023-08-21",
    "rain": 0.0,
    "min_temp": null,
    "max_temp": null
  },
  {
    "date": "2023-08-25",
    "rain": 0.0,
    "min_temp": null,
    "max_temp": null
  },
  {
    "date": "2023-09-19",
    "rain": 21.0,
    "min_temp": null,
    "max_temp": null
  },
  {
    "date": "2023-09-28",
    "rain": 18.5,
    "min_temp": null,
    "max_temp": null
  },
  {
    "date": "2023-11-17",
    "rain": 37.9,
    "min_temp": null,
    "max_temp": null
  },
  {
    "date": "2023-11-29",
    "rain": 33.1,
    "min_temp": null,
    "max_temp": null
  },
  {
    "date": "2023-12-27",
    "rain": 23.5,
    "min_temp": null,
    "max_temp": null
  },
  {
    "date": "2023-12-28",
    "rain": 81.0,
    "min_temp": null,
    "max_temp": null
  },
  {
    "date": "2024-01-02",
    "rain": 112.0,
    "min_temp": null,
    "max_temp": null
  },
  {
    "date": "2024-01-09",
    "rain": 131.0,
    "min_temp": null,
    "max_temp": null
  },
  {
    "date": "2024-01-10",
    "rain": 130.0,
    "min_temp": null,
    "max_temp": null
  },
  {
    "date": "2024-01-16",
    "rain": 0.0,
    "min_temp": null,
    "max_temp": null
  },
  {
    "date": "2024-01-17",
    "rain": 0.0,
    "min_temp": null,
    "max_temp": null
  },
  {
    "date": "2024-01-18",
    "rain": 0.0,
    "min_temp": null,
    "max_temp": null
  },
  {
    "date": "2024-01-23",
    "rain": 0.0,
    "min_temp": null,
    "max_temp": null
  },
  {
    "date": "2024-01-25",
    "rain": 0.0,
    "min_temp": null,
    "max_temp": null
  },
  {
    "date": "2024-01-26",
    "rain": 0.0,
    "min_temp": null,
    "max_temp": null
  },
  {
    "date": "2024-01-30",
    "rain": 10.0,
    "min_temp": null,
    "max_temp": null
  },
  {
    "date": "2024-02-07",
    "rain": 0.0,
    "min_temp": null,
    "max_temp": null
  },
  {
    "date": "2024-02-09",
    "rain": 0.0,
    "min_temp": null,
    "max_temp": null
  },
  {
    "date": "2024-02-10",
    "rain": 0.0,
    "min_temp": null,
    "max_temp": null
  },
  {
    "date": "2024-02-11",
    "rain": 0.0,
    "min_temp": null,
    "max_temp": null
  },
  {
    "date": "2024-02-19",
    "rain": 0.0,
    "min_temp": null,
    "max_temp": null
  },
  {
    "date": "2024-02-20",
    "rain": 0.0,
    "min_temp": null,
    "max_temp": null
  },
  {
    "date": "2024-02-22",
    "rain": 0.0,
    "min_temp": null,
    "max_temp": null
  },
  {
    "date": "2024-02-26",
    "rain": 0.0,
    "min_temp": null,
    "max_temp": null
  },
  {
    "date": "2024-03-06",
    "rain": 0.0,
    "min_temp": null,
    "max_temp": null
  },
  {
    "date": "2024-03-12",
    "rain": 0.0,
    "min_temp": null,
    "max_temp": null
  },
  {
    "date": "2024-03-13",
    "rain": 0.0,
    "min_temp": null,
    "max_temp": null
  },
  {
    "date": "2024-03-17",
    "rain": 0.0,
    "min_temp": null,
    "max_temp": null
  },
  {
    "date": "2024-03-18",
    "rain": 0.0,
    "min_temp": null,
    "max_temp": null
  },
  {
    "date": "2024-03-19",
    "rain": 0.0,
    "min_temp": null,
    "max_temp": null
  },
  {
    "date": "2024-03-20",
    "rain": 0.0,
    "min_temp": null,
    "max_temp": null
  },
  {
    "date": "2024-03-26",
    "rain": 0.0,
    "min_temp": null,
    "max_temp": null
  },
  {
    "date": "2024-03-30",
    "rain": 0.0,
    "min_temp": null,
    "max_temp": null
  },
  {
    "date": "2024-03-31",
    "rain": 0.0,
    "min_temp": null,
    "max_temp": null
  },
  {
    "date": "2024-05-03",
    "rain": 0.0,
    "min_temp": null,
    "max_temp": null
  },
  {
    "date": "2024-07-22",
    "rain": 0.0,
    "min_temp": null,
    "max_temp": null
  },
  {
    "date": "2024-08-27",
    "rain": 0.0,
    "min_temp": null,
    "max_temp": null
  },
  {
    "date": "2024-10-18",
    "rain": 0.0,
    "min_temp": null,
    "max_temp": null
  },
  {
    "date": "2025-01-21",
    "rain": 90.6,
    "min_temp": null,
    "max_temp": null
  },
  {
    "date": "2025-02-03",
    "rain": 0.0,
    "min_temp": null,
    "max_temp": null
  },
  {
    "date": "2025-02-04",
    "rain": 0.0,
    "min_temp": null,
    "max_temp": null
  },
  {
    "date": "2025-02-05",
    "rain": 0.0,
    "min_temp": null,
    "max_temp": null
  },
  {
    "date": "2025-02-07",
    "rain": 0.0,
    "min_temp": null,
    "max_temp": null
  },
  {
    "date": "2025-02-17",
    "rain": 0.0,
    "min_temp": null,
    "max_temp": null
  },
  {
    "date": "2025-03-07",
    "rain": 0.0,
    "min_temp": null,
    "max_temp": null
  },
  {
    "date": "2025-04-02",
    "rain": 11.4,
    "min_temp": null,
    "max_temp": null
  },
  {
    "date": "2025-07-30",
    "rain": 0.0,
    "min_temp": null,
    "max_temp": null
  }
]