[
  {
    "date": "2024-04-11",
    "rain": 15.5,
    "min_temp": null,
    "max_temp": null
  },
  {
    "date": "2024-04-13",
    "rain": 27.0,
    "min_temp": null,
    "max_temp": null
  },
  {
    "date": "2024-04-30",
    "rain": 36.0,
    "min_temp": null,
    "max_temp": null
  },
  {
    "date": "2024-05-19",
    "rain": 77.0,
    "min_temp": null,
    "max_temp": null
  },
  {
    "date": "2024-05-20",
    "rain": 84.5,
    "min_temp": null,
    "max_temp": null
  },
  {
    "date": "2024-05-27",
    "rain": 49.5,
    "min_temp": null,
    "max_temp": null
  },
  {
    "date": "2024-06-03",
    "rain": 133.0,
    "min_temp": null,
    "max_temp": null
  },
  {
    "date": "2024-06-13",
    "rain": 16.5,
    "min_temp": null,
    "max_temp": null
  },
  {
    "date": "2024-06-14",
    "rain": 2.5,
    "min_temp": null,
    "max_temp": null
  },
  {
    "date": "2024-06-20",
    "rain": 27.0,
    "min_temp": null,
    "max_temp": null
  },
  {
    "date": "2024-06-26",
    "rain": 32.5,
    "min_temp": null,
    "max_temp": null
  },
  {
    "date": "2024-07-01",
    "rain": 19.0,
    "min_temp": null,
    "max_temp": null
  },
  {
    "date": "2024-07-03",
    "rain": 2.0,
    "min_temp": null,
    "max_temp": null
  },
  {
    "date": "2024-07-07",
    "rain": 2.5,
    "min_temp": null,
    "max_temp": null
  },
  {
    "date": "2024-07-13",
    "rain": 12.0,
    "min_temp": null,
    "max_temp": null
  },
  {
    "date": "2024-08-29",
    "rain": 1.0,
    "min_temp": null,
    "max_temp": null
  },
  {
    "date": "2024-09-04",
    "rain": 14.0,
    "min_temp": null,
    "max_temp": null
  },
  {
    "date": "2024-10-06",
    "rain": 9.0,
    "min_temp": null,
    "max_temp": null
  },
  {
    "date": "2024-10-08",
    "rain": 141.0,
    "min_temp": null,
    "max_temp": null
  },
  {
    "date": "2024-10-10",
    "rain": 50.0,
    "min_temp": null,
    "max_temp": null
  },
  {
    "date": "2024-10-14",
    "rain": 73.0,
    "min_temp": null,
    "max_temp": null
  },
  {
    "date": "2024-10-20",
    "rain": 7.5,
    "min_temp": null,
    "max_temp": null
  },
  {
    "date": "2024-10-31",
    "rain": 5.0,
    "min_temp": null,
    "max_temp": null
  },
  {
    "date": "2025-02-25",
    "rain": 8.0,
    "min_temp": null,
    "max_temp": null
  },
  {
    "date": "2025-03-14",
    "rain": 18.0,
    "min_temp": null,
    "max_temp": null
  },
  {
    "date": "2025-03-16",
    "rain": 10.0,
    "min_temp": null,
    "max_temp": null
  },
  {
    "date": "2025-03-20",
    "rain": 75.5,
    "min_temp": null,
    "max_temp": null
  },
  {
    "date": "2025-04-04",
    "rain": 75.5,
    "min_temp": null,
    "max_temp": null
  },
  {
    "date": "2025-04-07",
    "rain": 55.0,
    "min_temp": null,
    "max_temp": null
  },
  {
    "date": "2025-04-13",
    "rain": 6.0,
    "min_temp": null,
    "max_temp": null
  },
  {
    "date": "2025-06-27",
    "rain": 22.0,
    "min_temp": null,
    "max_temp": null
  },
  {
    "date": "2025-08-07",
    "rain": 0.5,
    "min_temp": null,
    "max_temp": null
  }
]