[
  {
    "date": "2024-01-30",
    "rain": 6.0,
    "temp_min": null,
    "temp_max": null
  },
  {
    "date": "2024-01-22",
    "rain": 0.1,
    "temp_min": null,
    "temp_max": null
  },
  {
    "date": "2024-01-12",
    "rain": 0.8,
    "temp_min": null,
    "temp_max": null
  },
  {
    "date": "2024-01-11",
    "rain": 97.5,
    "temp_min": null,
    "temp_max": null
  },
  {
    "date": "2024-01-04",
    "rain": 0.1,
    "temp_min": null,
    "temp_max": null
  },
  {
    "date": "2023-12-27",
    "rain": 23.6,
    "temp_min": null,
    "temp_max": null
  },
  {
    "date": "2023-12-20",
    "rain": 44.3,
    "temp_min": null,
    "temp_max": null
  },
  {
    "date": "2023-12-08",
    "rain": 150.6,
    "temp_min": null,
    "temp_max": null
  },
  {
    "date": "2023-11-27",
    "rain": 18.7,
    "temp_min": null,
    "temp_max": null
  },
  {
    "date": "2023-09-21",
    "rain": 5.6,
    "temp_min": null,
    "temp_max": null
  },
  {
    "date": "2023-08-23",
    "rain": 16.0,
    "temp_min": null,
    "temp_max": null
  },
  {
    "date": "2022-11-25",
    "rain": 0.5,
    "temp_min": null,
    "temp_max": null
  },
  {
    "date": "2022-11-21",
    "rain": 0.2,
    "temp_min": null,
    "temp_max": null
  },
  {
    "date": "2022-09-26",
    "rain": 51.0,
    "temp_min": null,
    "temp_max": null
  },
  {
    "date": "2022-03-07",
    "rain": 62.2,
    "temp_min": null,
    "temp_max": null
  },
  {
    "date": "2022-02-24",
    "rain": 42.5,
    "temp_min": null,
    "temp_max": null
  },
  {
    "date": "2022-02-08",
    "rain": 0.5,
    "temp_min": null,
    "temp_max": null
  },
  {
    "date": "2022-01-31",
    "rain": 22.5,
    "temp_min": null,
    "temp_max": null
  },
  {
    "date": "2022-01-07",
    "rain": 7.0,
    "temp_min": null,
    "temp_max": null
  },
  {
    "date": "2021-12-21",
    "rain": 16.8,
    "temp_min": null,
    "temp_max": null
  },
  {
    "date": "2021-11-24",
    "rain": 115.9,
    "temp_min": null,
    "temp_max": null
  },
  {
    "date": "2021-07-16",
    "rain": 3.6,
    "temp_min": null,
    "temp_max": null
  }
]