[
  {
    "date": "2019-11-25",
    "rain": 43.3,
    "min_temp": null,
    "max_temp": null
  },
  {
    "date": "2019-11-29",
    "rain": 96.0,
    "min_temp": null,
    "max_temp": null
  },
  {
    "date": "2020-01-22",
    "rain": 23.2,
    "min_temp": null,
    "max_temp": null
  },
  {
    "date": "2021-08-14",
    "rain": 2.4,
    "min_temp": null,
    "max_temp": null
  },
  {
    "date": "2021-09-26",
    "rain": 44.5,
    "min_temp": null,
    "max_temp": null
  },
  {
    "date": "2021-10-28",
    "rain": 29.6,
    "min_temp": null,
    "max_temp": null
  },
  {
    "date": "2021-11-11",
    "rain": 14.2,
    "min_temp": null,
    "max_temp": null
  },
  {
    "date": "2021-12-04",
    "rain": 9.4,
    "min_temp": null,
    "max_temp": null
  },
  {
    "date": "2021-12-11",
    "rain": 16.0,
    "min_temp": null,
    "max_temp": null
  },
  {
    "date": "2021-12-12",
    "rain": 10.0,
    "min_temp": null,
    "max_temp": null
  },
  {
    "date": "2021-12-14",
    "rain": 77.3,
    "min_temp": null,
    "max_temp": null
  },
  {
    "date": "2021-12-19",
    "rain": 23.4,
    "min_temp": null,
    "max_temp": null
  },
  {
    "date": "2022-01-09",
    "rain": 12.6,
    "min_temp": null,
    "max_temp": null
  },
  {
    "date": "2022-01-10",
    "rain": 70.9,
    "min_temp": null,
    "max_temp": null
  },
  {
    "date": "2022-02-01",
    "rain": 8.7,
    "min_temp": null,
    "max_temp": null
  },
  {
    "date": "2022-02-07",
    "rain": 4.8,
    "min_temp": null,
    "max_temp": null
  },
  {
    "date": "2022-02-08",
    "rain": 8.2,
    "min_temp": null,
    "max_temp": null
  },
  {
    "date": "2022-02-11",
    "rain": 34.8,
    "min_temp": null,
    "max_temp": null
  },
  {
    "date": "2022-02-19",
    "rain": 40.0,
    "min_temp": null,
    "max_temp": null
  },
  {
    "date": "2022-02-21",
    "rain": 9.5,
    "min_temp": null,
    "max_temp": null
  },
  {
    "date": "2022-02-26",
    "rain": 8.5,
    "min_temp": null,
    "max_temp": null
  },
  {
    "date": "2022-03-20",
    "rain": 3.0,
    "min_temp": null,
    "max_temp": null
  },
  {
    "date": "2022-04-01",
    "rain": 1.5,
    "min_temp": null,
    "max_temp": null
  },
  {
    "date": "2022-05-05",
    "rain": 9.5,
    "min_temp": null,
    "max_temp": null
  },
  {
    "date": "2022-07-27",
    "rain": 27.2,
    "min_temp": null,
    "max_temp": null
  },
  {
    "date": "2022-08-25",
    "rain": 2.5,
    "min_temp": null,
    "max_temp": null
  },
  {
    "date": "2022-09-21",
    "rain": 1.6,
    "min_temp": null,
    "max_temp": null
  },
  {
    "date": "2022-09-23",
    "rain": 2.4,
    "min_temp": null,
    "max_temp": null
  },
  {
    "date": "2022-10-06",
    "rain": 8.0,
    "min_temp": null,
    "max_temp": null
  },
  {
    "date": "2022-11-02",
    "rain": 65.5,
    "min_temp": null,
    "max_temp": null
  },
  {
    "date": "2022-11-06",
    "rain": 44.2,
    "min_temp": null,
    "max_temp": null
  },
  {
    "date": "2022-11-17",
    "rain": 4.5,
    "min_temp": null,
    "max_temp": null
  },
  {
    "date": "2022-12-19",
    "rain": 69.3,
    "min_temp": null,
    "max_temp": null
  },
  {
    "date": "2022-12-21",
    "rain": 22.2,
    "min_temp": null,
    "max_temp": null
  },
  {
    "date": "2023-01-09",
    "rain": 8.7,
    "min_temp": null,
    "max_temp": null
  },
  {
    "date": "2023-01-22",
    "rain": 59.9,
    "min_temp": null,
    "max_temp": null
  },
  {
    "date": "2023-01-28",
    "rain": 6.5,
    "min_temp": null,
    "max_temp": null
  },
  {
    "date": "2023-02-05",
    "rain": 16.4,
    "min_temp": null,
    "max_temp": null
  },
  {
    "date": "2023-02-06",
    "rain": 6.6,
    "min_temp": null,
    "max_temp": null
  },
  {
    "date": "2023-02-19",
    "rain": 9.0,
    "min_temp": null,
    "max_temp": null
  },
  {
    "date": "2023-02-20",
    "rain": 113.0,
    "min_temp": null,
    "max_temp": null
  },
  {
    "date": "2023-02-21",
    "rain": 31.2,
    "min_temp": null,
    "max_temp": null
  },
  {
    "date": "2023-03-02",
    "rain": 18.8,
    "min_temp": null,
    "max_temp": null
  },
  {
    "date": "2023-03-06",
    "rain": 2.0,
    "min_temp": null,
    "max_temp": null
  },
  {
    "date": "2023-03-14",
    "rain": 4.0,
    "min_temp": null,
    "max_temp": null
  },
  {
    "date": "2023-04-29",
    "rain": 25.4,
    "min_temp": null,
    "max_temp": null
  },
  {
    "date": "2023-04-30",
    "rain": 29.2,
    "min_temp": null,
    "max_temp": null
  },
  {
    "date": "2023-05-05",
    "rain": 65.0,
    "min_temp": null,
    "max_temp": null
  },
  {
    "date": "2023-05-31",
    "rain": 25.0,
    "min_temp": null,
    "max_temp": null
  },
  {
    "date": "2023-07-03",
    "rain": 5.2,
    "min_temp": null,
    "max_temp": null
  },
  {
    "date": "2023-10-08",
    "rain": 10.0,
    "min_temp": null,
    "max_temp": null
  },
  {
    "date": "2023-11-27",
    "rain": 20.5,
    "min_temp": null,
    "max_temp": null
  },
  {
    "date": "2023-12-13",
    "rain": 40.0,
    "min_temp": null,
    "max_temp": null
  },
  {
    "date": "2023-12-16",
    "rain": 87.1,
    "min_temp": null,
    "max_temp": null
  },
  {
    "date": "2023-12-28",
    "rain": 87.1,
    "min_temp": null,
    "max_temp": null
  },
  {
    "date": "2023-12-29",
    "rain": 84.7,
    "min_temp": null,
    "max_temp": null
  },
  {
    "date": "2023-12-30",
    "rain": 86.2,
    "min_temp": null,
    "max_temp": null
  },
  {
    "date": "2024-01-07",
    "rain": 15.9,
    "min_temp": null,
    "max_temp": null
  },
  {
    "date": "2024-01-09",
    "rain": 79.1,
    "min_temp": null,
    "max_temp": null
  },
  {
    "date": "2024-01-11",
    "rain": 128.0,
    "min_temp": null,
    "max_temp": null
  },
  {
    "date": "2024-01-22",
    "rain": 3.0,
    "min_temp": null,
    "max_temp": null
  },
  {
    "date": "2024-02-15",
    "rain": 8.6,
    "min_temp": null,
    "max_temp": null
  },
  {
    "date": "2024-02-17",
    "rain": 2.2,
    "min_temp": null,
    "max_temp": null
  },
  {
    "date": "2024-02-27",
    "rain": 8.3,
    "min_temp": null,
    "max_temp": null
  },
  {
    "date": "2024-02-28",
    "rain": 4.0,
    "min_temp": null,
    "max_temp": null
  },
  {
    "date": "2024-03-21",
    "rain": 14.7,
    "min_temp": null,
    "max_temp": null
  },
  {
    "date": "2024-03-27",
    "rain": 24.6,
    "min_temp": null,
    "max_temp": null
  },
  {
    "date": "2024-04-13",
    "rain": 43.2,
    "min_temp": null,
    "max_temp": null
  },
  {
    "date": "2024-04-15",
    "rain": 73.5,
    "min_temp": null,
    "max_temp": null
  },
  {
    "date": "2024-08-04",
    "rain": 5.6,
    "min_temp": null,
    "max_temp": null
  },
  {
    "date": "2024-10-06",
    "rain": 11.5,
    "min_temp": null,
    "max_temp": null
  },
  {
    "date": "2024-10-09",
    "rain": 83.3,
    "min_temp": null,
    "max_temp": null
  },
  {
    "date": "2024-10-17",
    "rain": 14.1,
    "min_temp": null,
    "max_temp": null
  },
  {
    "date": "2024-12-23",
    "rain": 11.4,
    "min_temp": null,
    "max_temp": null
  },
  {
    "date": "2025-01-16",
    "rain": 30.2,
    "min_temp": null,
    "max_temp": null
  },
  {
    "date": "2025-01-23",
    "rain": 29.2,
    "min_temp": null,
    "max_temp": null
  },
  {
    "date": "2025-01-31",
    "rain": 20.2,
    "min_temp": null,
    "max_temp": null
  },
  {
    "date": "2025-02-11",
    "rain": 7.5,
    "min_temp": null,
    "max_temp": null
  },
  {
    "date": "2025-02-27",
    "rain": 87.6,
    "min_temp": null,
    "max_temp": null
  },
  {
    "date": "2025-03-03",
    "rain": 143.8,
    "min_temp": null,
    "max_temp": null
  },
  {
    "date": "2025-03-12",
    "rain": 72.0,
    "min_temp": null,
    "max_temp": null
  },
  {
    "date": "2025-03-16",
    "rain": 20.2,
    "min_temp": null,
    "max_temp": null
  },
  {
    "date": "2025-03-31",
    "rain": 22.0,
    "min_temp": null,
    "max_temp": null
  },
  {
    "date": "2025-04-09",
    "rain": 26.5,
    "min_temp": null,
    "max_temp": null
  }
]