{
  "pdf_path": "/tmp/weather_lk/pdf_meteo_gov_lk/6b86eea0b53452e4d57c45829fab3b10.pdf",
  "date_ut": 1630607400.0,
  "date": "2021-09-03",
  "weather_list": [
    {
      "place": "Anuradhapura",
      "min_temp": 22.9,
      "max_temp": 29.4,
      "rain": 35.9,
      "lat": 8.311351799999999,
      "lng": 80.4036508
    },
    {
      "place": "Badulla",
      "min_temp": 18.4,
      "max_temp": 27.2,
      "rain": 0.2,
      "lat": 6.993400899999999,
      "lng": 81.0549815
    },
    {
      "place": "Bandarawela",
      "min_temp": 16.7,
      "max_temp": 25.1,
      "rain": 0,
      "lat": 6.825877999999999,
      "lng": 80.9981576
    },
    {
      "place": "Batticaloa",
      "min_temp": 26.3,
      "max_temp": 30.6,
      "rain": 0.0,
      "lat": 7.7249146,
      "lng": 81.6966911
    },
    {
      "place": "Colombo",
      "min_temp": 24.5,
      "max_temp": 30.3,
      "rain": 11.4,
      "lat": 6.9270786,
      "lng": 79.861243
    },
    {
      "place": "Galle",
      "min_temp": 23.9,
      "max_temp": 28.1,
      "rain": 11.5,
      "lat": 6.032894799999999,
      "lng": 80.2167912
    },
    {
      "place": "Hambanthota",
      "min_temp": 23.9,
      "max_temp": 28.1,
      "rain": 5.4,
      "lat": 6.1428829,
      "lng": 81.12123079999999
    },
    {
      "place": "Jaffna",
      "min_temp": 24.0,
      "max_temp": 32.5,
      "rain": 11.1,
      "lat": 9.6614981,
      "lng": 80.02554649999999
    },
    {
      "place": "Monaragala",
      "min_temp": 21.7,
      "max_temp": 31.0,
      "rain": 0.1,
      "lat": 6.890645399999999,
      "lng": 81.34544170000001
    },
    {
      "place": "Katugasthota",
      "min_temp": 21.3,
      "max_temp": 27.1,
      "rain": 9.4,
      "lat": 7.3251558,
      "lng": 80.62297869999999
    },
    {
      "place": "Katunayake",
      "min_temp": 25.3,
      "max_temp": 30.3,
      "rain": 0.0,
      "lat": 7.172484899999999,
      "lng": 79.8853484
    },
    {
      "place": "Kurunagala",
      "min_temp": 24.6,
      "max_temp": 30.4,
      "rain": 1.1,
      "lat": 7.4817695,
      "lng": 80.3608876
    },
    {
      "place": "Maha Illuppallama",
      "min_temp": 25.3,
      "max_temp": 31.4,
      "rain": 0.0,
      "lat": 8.1155443,
      "lng": 80.47207639999999
    },
    {
      "place": "Mannar",
      "min_temp": 22.8,
      "max_temp": 30.2,
      "rain": 58.6,
      "lat": 8.980974300000002,
      "lng": 79.90441489999999
    },
    {
      "place": "Polonnaruwa",
      "min_temp": 27.2,
      "max_temp": 32.6,
      "rain": 0.0,
      "lat": 7.940338400000001,
      "lng": 81.0187984
    },
    {
      "place": "Nuwara Eliya",
      "min_temp": 13.0,
      "max_temp": 17.4,
      "rain": 2.9,
      "lat": 6.949716599999999,
      "lng": 80.7891068
    },
    {
      "place": "Pothuvil",
      "min_temp": 25.0,
      "max_temp": 31.7,
      "rain": 0.0,
      "lat": 6.875270599999999,
      "lng": 81.8306334
    },
    {
      "place": "Puttalam",
      "min_temp": 25.4,
      "max_temp": 30.8,
      "rain": 5.6,
      "lat": 8.0407913,
      "lng": 79.839386
    },
    {
      "place": "Rathmalana",
      "min_temp": 25.3,
      "max_temp": 31.6,
      "rain": 4.5,
      "lat": 6.8195453,
      "lng": 79.8800832
    },
    {
      "place": "Rathnapura",
      "min_temp": 23.0,
      "max_temp": 28.5,
      "rain": 2.6,
      "lat": 6.7055742,
      "lng": 80.3847345
    },
    {
      "place": "Trincomalee",
      "min_temp": 23.1,
      "max_temp": 32.0,
      "rain": 0.3,
      "lat": 8.5873638,
      "lng": 81.2152121
    },
    {
      "place": "Vavuniya",
      "min_temp": 22.5,
      "max_temp": 31.2,
      "rain": 0.9,
      "lat": 8.7542029,
      "lng": 80.4982402
    },
    {
      "place": "Mattla",
      "min_temp": 23.6,
      "max_temp": 30.8,
      "rain": 0.7,
      "lat": 6.288780374382144,
      "lng": 81.12460077774537
    },
    {
      "place": "Mullaithivu",
      "min_temp": 23.1,
      "max_temp": 32.6,
      "rain": 0.5,
      "lat": 9.2670911,
      "lng": 80.81424799999999
    },
    {
      "place": "Castlereigh",
      "rain": 10.0,
      "min_temp": null,
      "max_temp": null,
      "lat": 6.8577186,
      "lng": 80.5855038
    },
    {
      "place": "Randenigala",
      "rain": 0.0,
      "min_temp": null,
      "max_temp": null,
      "lat": 7.188888899999999,
      "lng": 80.92500000000001
    },
    {
      "place": "Norton",
      "rain": 60.8,
      "min_temp": null,
      "max_temp": null,
      "lat": 6.9168796,
      "lng": 80.5171737
    },
    {
      "place": "Rantambe",
      "rain": 0.0,
      "min_temp": null,
      "max_temp": null,
      "lat": 7.1910444,
      "lng": 80.9463464
    },
    {
      "place": "Maussakele",
      "rain": 0.0,
      "min_temp": null,
      "max_temp": null,
      "lat": 6.8645162,
      "lng": 80.52717559999999
    },
    {
      "place": "Bowatenna",
      "rain": 0.0,
      "min_temp": null,
      "max_temp": null,
      "lat": 7.671017399999998,
      "lng": 80.65627529999999
    },
    {
      "place": "Canyon",
      "rain": 11.8,
      "min_temp": null,
      "max_temp": null,
      "lat": 6.87025261687585,
      "lng": 80.52581841045284
    },
    {
      "place": "Ukuwela",
      "rain": 12.1,
      "min_temp": null,
      "max_temp": null,
      "lat": 7.423462299999999,
      "lng": 80.6306103
    },
    {
      "place": "Lakshapana",
      "rain": 63.7,
      "min_temp": null,
      "max_temp": null,
      "lat": 6.9247584,
      "lng": 80.491047
    },
    {
      "place": "Samanala Wawa",
      "rain": 0.0,
      "min_temp": null,
      "max_temp": null,
      "lat": 6.6788795,
      "lng": 80.79936459999999
    },
    {
      "place": "Upper Kotmale",
      "rain": 13.5,
      "min_temp": null,
      "max_temp": null,
      "lat": 6.9389539,
      "lng": 80.663037
    },
    {
      "place": "Kukuleganaga",
      "rain": 4.0,
      "min_temp": null,
      "max_temp": null,
      "lat": 6.582781400000001,
      "lng": 80.23423249999999
    },
    {
      "place": "Kotmale",
      "rain": 15.5,
      "min_temp": null,
      "max_temp": null,
      "lat": 7.0223089,
      "lng": 80.5910567
    },
    {
      "place": "Victoriya",
      "rain": 0.0,
      "min_temp": null,
      "max_temp": null,
      "lat": 7.873053999999999,
      "lng": 80.77179699999999
    },
    {
      "place": "Ranorava",
      "rain": 80.0,
      "min_temp": null,
      "max_temp": null,
      "lat": 7.873053999999999,
      "lng": 80.77179699999999
    },
    {
      "place": "Watawala",
      "rain": 26.7,
      "min_temp": null,
      "max_temp": null,
      "lat": 6.944946799999999,
      "lng": 80.53898339999999
    },
    {
      "place": "Thalangaha Estate",
      "rain": 57.8,
      "min_temp": null,
      "max_temp": null,
      "lat": 6.1467663,
      "lng": 80.3438001
    },
    {
      "place": "Kotagala Rosita",
      "rain": 25.5,
      "min_temp": null,
      "max_temp": null,
      "lat": 6.929680599999999,
      "lng": 80.6049374
    },
    {
      "place": "Baddegama",
      "rain": 55.7,
      "min_temp": null,
      "max_temp": null,
      "lat": 6.168829199999999,
      "lng": 80.1793976
    },
    {
      "place": "Elephant Pass",
      "rain": 24.3,
      "min_temp": null,
      "max_temp": null,
      "lat": 9.5044995,
      "lng": 80.402048
    },
    {
      "place": "Madulkale",
      "rain": 55.4,
      "min_temp": null,
      "max_temp": null,
      "lat": 7.399152799999999,
      "lng": 80.73345549999999
    },
    {
      "place": "Kethendola",
      "rain": 24.1,
      "min_temp": null,
      "max_temp": null,
      "lat": 7.873053999999999,
      "lng": 80.77179699999999
    },
    {
      "place": "Mapalana",
      "rain": 40.4,
      "min_temp": null,
      "max_temp": null,
      "lat": 6.7681194,
      "lng": 80.4715866
    },
    {
      "place": "Port Authority",
      "rain": 23.9,
      "min_temp": null,
      "max_temp": null,
      "lat": 7.873053999999999,
      "lng": 80.77179699999999
    },
    {
      "place": "Mihinthale",
      "rain": 32.0,
      "min_temp": null,
      "max_temp": null,
      "lat": 8.358457699999999,
      "lng": 80.511702
    },
    {
      "place": "Bata Atha",
      "rain": 22.5,
      "min_temp": null,
      "max_temp": null,
      "lat": 6.109917299999999,
      "lng": 80.901416
    },
    {
      "place": "Point Pedro",
      "rain": 30.4,
      "min_temp": null,
      "max_temp": null,
      "lat": 9.7937885,
      "lng": 80.2209773
    },
    {
      "place": "Poddiwela Farm",
      "rain": 22.0,
      "min_temp": null,
      "max_temp": null,
      "lat": 6.766339299999999,
      "lng": 79.8892005
    },
    {
      "place": "Shettikulam",
      "rain": 30.0,
      "min_temp": null,
      "max_temp": null,
      "lat": 8.665595600000001,
      "lng": 80.2962385
    },
    {
      "place": "Omanthai",
      "rain": 22.0,
      "min_temp": null,
      "max_temp": null,
      "lat": 8.872387,
      "lng": 80.5077237
    },
    {
      "place": "Atchuvely",
      "rain": 28.3,
      "min_temp": null,
      "max_temp": null,
      "lat": 9.7786397,
      "lng": 80.1160651
    },
    {
      "place": "Yakawawa",
      "rain": 21.6,
      "min_temp": null,
      "max_temp": null,
      "lat": 7.873053999999999,
      "lng": 80.77179699999999
    },
    {
      "place": "Monrovia",
      "rain": 28.3,
      "min_temp": null,
      "max_temp": null,
      "lat": 7.873053999999999,
      "lng": 80.77179699999999
    },
    {
      "place": "Benthotawatta",
      "rain": 21.0,
      "min_temp": null,
      "max_temp": null,
      "lat": 7.873053999999999,
      "lng": 80.77179699999999
    }
  ],
  "max_rain": {
    "max_rain": 80.0,
    "max_rain_place": "Ranorava"
  },
  "min_temp": {
    "min_temp": 13.0,
    "min_temp_place": "Nuwara Eliya"
  },
  "max_temp": {
    "max_temp": 32.6,
    "max_temp_place": "Polonnaruwa"
  }
}